pyphyskit/__init__.py
pyphyskit/calculus.py
pyphyskit/coordinate_converter.py
pyphyskit/vectors.py
pyphyskit-0.0.1.dist-info/licenses/LICENSE
pyphyskit-0.0.1.dist-info/METADATA
pyphyskit-0.0.1.dist-info/WHEEL
pyphyskit-0.0.1.dist-info/top_level.txt
pyphyskit-0.0.1.dist-info/RECORD
