Metadata-Version: 2.4
Name: pyphyskit
Version: 0.0.1
Summary: Initial Release with Preliminary features
Author: Satkar Juneja
License: MIT License
Project-URL: Homepage, https://github.com/satkarjuneja/pyphyskit
Classifier: Programming Language :: Python :: 3
Classifier: License :: OSI Approved :: MIT License
Classifier: Operating System :: OS Independent
Requires-Python: >=3.10
License-File: LICENSE
Dynamic: license-file
